LyScriptTools64/__init__.py
LyScriptTools64-1.0.6.dist-info/LICENSE
LyScriptTools64-1.0.6.dist-info/METADATA
LyScriptTools64-1.0.6.dist-info/WHEEL
LyScriptTools64-1.0.6.dist-info/top_level.txt
LyScriptTools64-1.0.6.dist-info/RECORD
