Metadata-Version: 2.1
Name: LyScriptTools64
Version: 1.0.6
Summary: A powerful x64dbg remote debugging module tools
Home-page: UNKNOWN
Author: lyshark
Author-email: me@lyshark.com
License: MIT Licence
Platform: any
Requires-Python: >=3.6.0
